alibabacloud_serverless20210924/__init__.py
alibabacloud_serverless20210924/client.py
alibabacloud_serverless20210924/models.py
alibabacloud_serverless20210924-1.1.10.dist-info/LICENSE
alibabacloud_serverless20210924-1.1.10.dist-info/METADATA
alibabacloud_serverless20210924-1.1.10.dist-info/WHEEL
alibabacloud_serverless20210924-1.1.10.dist-info/top_level.txt
alibabacloud_serverless20210924-1.1.10.dist-info/RECORD
